transfer/__init__.py
transfer/__main__.py
transfer/_version.py
transfer/command_line.py
transfer/core.py
transfer/mapping.py
transfer/parser.py
transfer/paste_api.py
transfer/utils.py
transfer/version.py
file_transfer_tools-0.0.3.dist-info/LICENSE
file_transfer_tools-0.0.3.dist-info/METADATA
file_transfer_tools-0.0.3.dist-info/WHEEL
file_transfer_tools-0.0.3.dist-info/entry_points.txt
file_transfer_tools-0.0.3.dist-info/top_level.txt
file_transfer_tools-0.0.3.dist-info/RECORD
