Metadata-Version: 2.1
Name: file-transfer-tools
Version: 0.0.3
Summary: Transfer files simply in shell
Home-page: https://github.com/wyg1997/transfer
Author: wyg1997
Author-email: wangyinggang@foxmail.com
Classifier: Programming Language :: Python :: 3
Classifier: License :: OSI Approved :: Apache Software License
Requires-Python: >=3.6
License-File: LICENSE
Requires-Dist: requests
Requires-Dist: beautifulsoup4
